odoo/addons/l10n_br_stock/README.rst
odoo/addons/l10n_br_stock/__init__.py
odoo/addons/l10n_br_stock/__manifest__.py
odoo/addons/l10n_br_stock/hooks.py
odoo/addons/l10n_br_stock/demo/res_company_demo.xml
odoo/addons/l10n_br_stock/demo/res_users_demo.xml
odoo/addons/l10n_br_stock/demo/stock_location_demo.xml
odoo/addons/l10n_br_stock/i18n/es.po
odoo/addons/l10n_br_stock/i18n/l10n_br_stock.pot
odoo/addons/l10n_br_stock/i18n/pt_BR.po
odoo/addons/l10n_br_stock/models/__init__.py
odoo/addons/l10n_br_stock/models/stock_picking.py
odoo/addons/l10n_br_stock/readme/CONFIGURE.md
odoo/addons/l10n_br_stock/readme/CONTRIBUTORS.md
odoo/addons/l10n_br_stock/readme/DESCRIPTION.md
odoo/addons/l10n_br_stock/readme/HISTORY.md
odoo/addons/l10n_br_stock/readme/INSTALL.md
odoo/addons/l10n_br_stock/readme/USAGE.md
odoo/addons/l10n_br_stock/static/description/icon.png
odoo/addons/l10n_br_stock/static/description/index.html
odoo/addons/l10n_br_stock/views/stock_picking_view.xml
odoo_addon_l10n_br_stock-16.0.3.0.0.dist-info/METADATA
odoo_addon_l10n_br_stock-16.0.3.0.0.dist-info/WHEEL
odoo_addon_l10n_br_stock-16.0.3.0.0.dist-info/top_level.txt
odoo_addon_l10n_br_stock-16.0.3.0.0.dist-info/RECORD
